mlflowgo/__init__.py
mlflowgo/artifact_base.py
mlflowgo/artifact_logger.py
mlflowgo/base.py
mlflowgo/classifier.py
mlflowgo/mlflowgo.py
mlflowgo/regressor.py
mlflowgo/tournament.py
mlflowgo-1.0.2.dist-info/LICENSE.txt
mlflowgo-1.0.2.dist-info/METADATA
mlflowgo-1.0.2.dist-info/WHEEL
mlflowgo-1.0.2.dist-info/RECORD
