Metadata-Version: 2.1
Name: mlflowgo
Version: 1.0.2
Summary: 
Author: Jimmy Weaver
Requires-Python: >=3.11,<4.0
Classifier: Programming Language :: Python :: 3
Classifier: Programming Language :: Python :: 3.11
Classifier: Programming Language :: Python :: 3.12
Requires-Dist: flake8 (>=6.1.0,<7.0.0)
Requires-Dist: lightgbm (>=4.1.0,<5.0.0)
Requires-Dist: mlflow (>=2.9.2,<3.0.0)
Requires-Dist: pytest (>=7.4.3,<8.0.0)
Requires-Dist: scikit-learn (>=1.3.2,<2.0.0)
Requires-Dist: shap (>=0.43.0,<0.44.0)
Requires-Dist: xgboost (>=2.0.2,<3.0.0)
